pygamePhysics/__init__.py
pygamePhysics/collisions.py
pygamePhysics/physics.py
PygamePhysics-0.0.1.dist-info/METADATA
PygamePhysics-0.0.1.dist-info/WHEEL
PygamePhysics-0.0.1.dist-info/top_level.txt
PygamePhysics-0.0.1.dist-info/RECORD
