Metadata-Version: 2.1
Name: PygamePhysics
Version: 0.0.1
Summary: Help with physics in Pygame
Home-page: https://github.com/SeventyFox92475/pygamePhysics
Author: Ethan Culp
Author-email: ethan.culp101@gmail.com
License: UNKNOWN
Platform: UNKNOWN
Classifier: Programming Language :: Python :: 3
Classifier: License :: OSI Approved :: MIT License
Classifier: Operating System :: OS Independent
Requires-Python: >=3.5
